aifashion/__init__.py
aifashion/af_functions.py
aifashion/af_oauth2.py
aifashion/apis.json
aifashion/cli/__init__.py
aifashion/cli/convert.py
aifashion/cli/info.py
aifashion/cli/main.py
aifashion_sdk-1.2.0.dist-info/METADATA
aifashion_sdk-1.2.0.dist-info/WHEEL
aifashion_sdk-1.2.0.dist-info/top_level.txt
aifashion_sdk-1.2.0.dist-info/RECORD
