Metadata-Version: 2.1
Name: aifashion-sdk
Version: 1.2.0
Summary: AIFashion® Python SDK
Home-page: UNKNOWN
Author: Sky Zhang
Author-email: sky.atomse@gmail.com
Maintainer: Sky Zhang
Maintainer-email: sky.atomse@gmail.com
License: MIT License
Platform: Linux
Platform: Darwin
Platform: Windows
Classifier: Development Status :: 4 - Beta
Classifier: Operating System :: MacOS
Classifier: Operating System :: POSIX
Classifier: Operating System :: Microsoft
Classifier: Operating System :: Microsoft :: Windows :: Windows NT/2000
Classifier: Operating System :: POSIX :: BSD
Classifier: Operating System :: POSIX :: BSD :: FreeBSD
Classifier: Operating System :: POSIX :: BSD :: NetBSD
Classifier: Operating System :: POSIX :: BSD :: OpenBSD
Classifier: Operating System :: POSIX :: Linux
Classifier: Operating System :: POSIX :: SunOS/Solaris
Classifier: License :: OSI Approved :: MIT License
Classifier: Programming Language :: Python
Classifier: Programming Language :: Python :: Implementation
Classifier: Programming Language :: Python :: 3
Classifier: Programming Language :: Python :: 3.5
Classifier: Programming Language :: Python :: 3.6
Classifier: Programming Language :: Python :: 3.7
Requires-Python: >=3
Requires-Dist: requests (>=2.22.0)
Requires-Dist: PyYAML (>=5.1.1)
Provides-Extra: docs
Requires-Dist: sphinx ; extra == 'docs'
Requires-Dist: sphinxcontrib-programoutput ; extra == 'docs'
Requires-Dist: sphinx-rtd-theme ; extra == 'docs'
Requires-Dist: numpydoc ; extra == 'docs'
Provides-Extra: tests
Requires-Dist: pytest (>=4.0) ; extra == 'tests'
Requires-Dist: pytest-cov ; extra == 'tests'
